onefootball_network/__init__.py
onefootball_network/client.py
onefootball_network/models.py
tests/__init__.py
tests/test_client.py
tests/test_models.py
onefootball_network-0.1.1.dist-info/METADATA
onefootball_network-0.1.1.dist-info/WHEEL
onefootball_network-0.1.1.dist-info/top_level.txt
onefootball_network-0.1.1.dist-info/RECORD
