Metadata-Version: 2.1
Name: onefootball-network
Version: 0.1.1
Summary: UNKNOWN
Home-page: UNKNOWN
License: UNKNOWN
Platform: UNKNOWN
Requires-Dist: rich (>=5.1.0)
Requires-Dist: pydantic (==1.6.1)
Requires-Dist: requests (==2.24.0)
Requires-Dist: lxml (==4.5.2)
Provides-Extra: dev
Requires-Dist: jupyterlab (>=0.35.4) ; extra == 'dev'
Requires-Dist: pytest (>=4.0.2) ; extra == 'dev'
Requires-Dist: black (>=19.3b0) ; extra == 'dev'
Requires-Dist: flake8 (>=3.6.0) ; extra == 'dev'
Requires-Dist: flake8-annotations (==2.1.0) ; extra == 'dev'
Requires-Dist: flake8-bandit (==2.1.2) ; extra == 'dev'
Requires-Dist: flake8-bugbear (==20.1.4) ; extra == 'dev'
Requires-Dist: flake8-docstrings (==1.5.0) ; extra == 'dev'
Requires-Dist: darglint (==1.4.0) ; extra == 'dev'
Requires-Dist: pre-commit (>=2.2.0) ; extra == 'dev'
Requires-Dist: mkdocs (>=1.1) ; extra == 'dev'
Requires-Dist: mkdocs-material (==4.6.3) ; extra == 'dev'
Requires-Dist: mkdocstrings (>=0.11.0) ; extra == 'dev'
Provides-Extra: docs
Requires-Dist: mkdocs ; extra == 'docs'
Requires-Dist: mkdocs-material (==4.6.3) ; extra == 'docs'
Requires-Dist: mkdocs-material-extensions (==1.0b2) ; extra == 'docs'
Requires-Dist: mkdocs-git-revision-date-localized-plugin (==0.5.0) ; extra == 'docs'
Requires-Dist: mkdocstrings ; extra == 'docs'
